[

  {
    "timestamp": "2025-07-29T22:53:16.052551",
    "user": "admin1@example.com",
    "action": "login",
    "details": "User logged in successfully"
  },
  {
    "timestamp": "2025-07-29T22:53:41.276374",
    "user": "admin1@example.com",
    "action": "login",
    "details": "User logged in successfully"
  },
  {"timestamp": "2025-07-29T23:16:19.336602", "user": "admin1@example.com", "action": "login", "details": "User logged in successfully"},
  {"timestamp": "2025-07-29T23:18:59.32131", "user": "emp1@example.com", "action": "login", "details": "User logged in successfully"},
  {"timestamp": "2025-07-29T23:20:37.276168", "user": "admin1@example.com", "action": "login", "details": "User logged in successfully"},
  {"timestamp": "2025-07-29T23:31:39.408754", "user": "emp1@example.com", "action": "login", "details": "User logged in successfully"},
  {"timestamp": "2025-07-30T00:23:42.87754", "user": "admin1@example.com", "action": "login", "details": "User logged in successfully"},
  {"timestamp": "2025-07-30T00:56:11.590446", "user": "admin1@example.com", "action": "login", "details": "User logged in successfully"},
  {"timestamp": "2025-07-30T00:57:37.657445", "user": "admin1@example.com", "action": "login", "details": "User logged in successfully"},
  {"timestamp": "2025-07-30T09:31:59.364589", "user": "admin1@example.com", "action": "login", "details": "User logged in successfully"},
  {"timestamp": "2025-07-30T09:44:36.18579", "user": "admin1@example.com", "action": "login", "details": "User logged in successfully"},
  {"timestamp": "2025-07-30T09:45:39.515114", "user": "admin1@example.com", "action": "Add Product", "details": "ID: 20, Name: Ghee, Price: 10.49, Quantity: 0"},
  {"timestamp": "2025-07-30T09:50:48.845415", "user": "admin1@example.com", "action": "login", "details": "User logged in successfully"},
  {"timestamp": "2025-07-30T09:51:19.118362", "user": "admin1@example.com", "action": "Restock Product", "details": "ID: 13, Name: Bread, Old Quantity: 6, New Quantity: 7"},
  {"timestamp": "2025-07-30T09:51:19.280822", "user": "admin1@example.com", "action": "Restock Product", "details": "ID: 13, Name: Bread, Old Quantity: 7, New Quantity: 8"},
  {"timestamp": "2025-07-30T10:01:13.724552", "user": "admin1@example.com", "action": "login", "details": "User logged in successfully"},
  {"timestamp": "2025-07-30T10:01:17.61887", "user": "admin1@example.com", "action": "Restock Product", "details": "ID: 13, Name: Bread, Old Quantity: 8, New Quantity: 9"},
  {"timestamp": "2025-07-30T10:01:30.162956", "user": "admin1@example.com", "action": "Restocked Product", "details": "Product: Bread, Old Qty: 9, New Qty: 10"},
  {"timestamp": "2025-07-30T10:25:55.37108", "user": "admin1@example.com", "action": "login", "details": "User logged in successfully"},
  {"timestamp": "2025-07-30T10:26:09.953027", "user": "admin1@example.com", "action": "Add Product", "details": "ID: 21, Name: Mouse, Price: 12.00, Quantity: 0"},
  {"timestamp": "2025-07-30T10:26:26.123352", "user": "admin1@example.com", "action": "Restocked Product", "details": "Product: Mouse, Old Qty: 0, New Qty: 1"},
  {"timestamp": "2025-07-30T10:26:26.853512", "user": "admin1@example.com", "action": "Restocked Product", "details": "Product: Mouse, Old Qty: 1, New Qty: 2"},
  {"timestamp": "2025-07-30T10:27:06.500143", "user": "admin1@example.com", "action": "ORDER_PLACED", "details": "Products: [Mouse (x1), Apple (x1)], Total: $21.50"},
  {"timestamp": "2025-07-30T10:34:20.718114", "user": "admin1@example.com", "action": "login", "details": "User logged in successfully"},
  {"timestamp": "2025-07-30T10:35:48.014854", "user": "admin1@example.com", "action": "Restocked Product", "details": "Product: Papaya, Old Qty: 0, New Qty: 1"},
  {"timestamp": "2025-07-30T10:35:48.377717", "user": "admin1@example.com", "action": "Restocked Product", "details": "Product: Papaya, Old Qty: 1, New Qty: 2"},
  {"timestamp": "2025-07-30T10:35:49.055669", "user": "admin1@example.com", "action": "Restocked Product", "details": "Product: Orange, Old Qty: 0, New Qty: 1"},
  {"timestamp": "2025-07-30T10:35:49.254663", "user": "admin1@example.com", "action": "Restocked Product", "details": "Product: Orange, Old Qty: 1, New Qty: 2"},
  {"timestamp": "2025-07-30T10:35:51.054757", "user": "admin1@example.com", "action": "Restocked Product", "details": "Product: Mouse, Old Qty: 1, New Qty: 2"},
  {"timestamp": "2025-07-30T10:43:01.864127", "user": "admin1@example.com", "action": "login", "details": "User logged in successfully"},
  {"timestamp": "2025-07-30T10:55:57.408305", "user": "admin1@example.com", "action": "login", "details": "User logged in successfully"},
  {"timestamp": "2025-07-30T10:56:18.70329", "user": "admin1@example.com", "action": "ORDER_PLACED", "details": "Products: [Milk (x1)], Total: $1.99"},
  {"timestamp": "2025-08-06T12:14:09.780994", "user": "admin1@example.com", "action": "login", "details": "User logged in successfully"},
  {"timestamp": "2025-08-06T12:14:27.797396", "user": "emp1@example.com", "action": "login", "details": "User logged in successfully"},
  {"timestamp": "2025-08-06T12:15:18.609885", "user": "admin1@example.com", "action": "login", "details": "User logged in successfully"},
  {"timestamp": "2025-08-06T12:15:35.682075", "user": "emp1@example.com", "action": "login", "details": "User logged in successfully"},
  {"timestamp": "2025-08-06T12:20:59.135015", "user": "admin1@example.com", "action": "login", "details": "User logged in successfully"},
  {"timestamp": "2025-08-06T12:21:14.867274", "user": "admin1@example.com", "action": "login", "details": "User logged in successfully"},
  {"timestamp": "2025-08-06T12:21:26.498104", "user": "admin1@example.com", "action": "login", "details": "User logged in successfully"},
  {"timestamp": "2025-08-06T12:22:44.945223", "user": "admin1@example.com", "action": "login", "details": "User logged in successfully"},
  {"timestamp": "2025-08-06T12:23:04.214516", "user": "emp1@example.com", "action": "login", "details": "User logged in successfully"},
  {"timestamp": "2025-08-06T12:23:24.482441", "user": "emp1@example.com", "action": "login", "details": "User logged in successfully"}
]